basix/__init__.py
basix/classes.py
basix/files.py
basix/functions.py
basix/numbers.py
basix/parquet.py
basix/viz.py
basix/yaml.py
basix-0.0.13.dist-info/LICENSE
basix-0.0.13.dist-info/METADATA
basix-0.0.13.dist-info/WHEEL
basix-0.0.13.dist-info/top_level.txt
basix-0.0.13.dist-info/RECORD
