Metadata-Version: 2.1
Name: basix
Version: 0.0.13
Summary: Utils for python
Author: Eduardo M. de Morais
Author-email: emdemor415@gmail.com
License: MIT License
License-File: LICENSE
Requires-Dist: numpy
Requires-Dist: scipy
Requires-Dist: pandas
Requires-Dist: setuptools
Requires-Dist: tqdm
Requires-Dist: scikit-learn
Requires-Dist: pyarrow
Requires-Dist: loguru
